cz_commitizen_hacknplan/__init__.py
cz_commitizen_hacknplan/__version__.py
cz_commitizen_hacknplan/cz_commitizen_hacknplan.py
cz_commitizen_hacknplan-0.0.7.dist-info/LICENSE
cz_commitizen_hacknplan-0.0.7.dist-info/METADATA
cz_commitizen_hacknplan-0.0.7.dist-info/WHEEL
cz_commitizen_hacknplan-0.0.7.dist-info/top_level.txt
cz_commitizen_hacknplan-0.0.7.dist-info/RECORD
