Metadata-Version: 2.1
Name: cz-commitizen-hacknplan
Version: 0.0.7
Summary: UNKNOWN
Home-page: https://github.com/CanisHelix/commitizen_hacknplan
Author: Nigel George
Author-email: nigel.george@shiroikuma.co.uk
License: MIT
Platform: UNKNOWN
Classifier: Programming Language :: Python :: 3
Classifier: License :: OSI Approved :: MIT License
Classifier: Operating System :: OS Independent
License-File: LICENSE
Requires-Dist: commitizen
